Workbook
Name BankName: Bank!$A$2:$A$421

Sheet sample_bulk
A1: amount | B1: currency | C1: accountNumber | D1: description | E1: bankName | F1: bankCode | G1: accountName
A2: 1 | B2: NGN | C2: 0780290893 | D2: Disbursement | E2: ACCESS BANK | F2: =IFERROR(VLOOKUP(E2, Bank!$A$2:$B$421, 2, FALSE), "") -> 000014 | G2: BLESSING OLAIYA
A3: 1 | B3: NGN | C3: 0242725710 | D3: Disbursement II | E3: WEMA BANK | F3: =IFERROR(VLOOKUP(E3, Bank!$A$2:$B$421, 2, FALSE), "") -> 000017 | G3: BLESSING DAMILOLA OLOFINYOKUN
F4: =IFERROR(VLOOKUP(E4, Bank!$A$2:$B$421, 2, FALSE), "")
F5: =IFERROR(VLOOKUP(E5, Bank!$A$2:$B$421, 2, FALSE), "")
F6: =IFERROR(VLOOKUP(E6, Bank!$A$2:$B$421, 2, FALSE), "")
F7: =IFERROR(VLOOKUP(E7, Bank!$A$2:$B$421, 2, FALSE), "")
F8: =IFERROR(VLOOKUP(E8, Bank!$A$2:$B$421, 2, FALSE), "")
F9: =IFERROR(VLOOKUP(E9, Bank!$A$2:$B$421, 2, FALSE), "")
F10: =IFERROR(VLOOKUP(E10, Bank!$A$2:$B$421, 2, FALSE), "")
F11: =IFERROR(VLOOKUP(E11, Bank!$A$2:$B$421, 2, FALSE), "")
F12: =IFERROR(VLOOKUP(E12, Bank!$A$2:$B$421, 2, FALSE), "")
F13: =IFERROR(VLOOKUP(E13, Bank!$A$2:$B$421, 2, FALSE), "")
F14: =IFERROR(VLOOKUP(E14, Bank!$A$2:$B$421, 2, FALSE), "")
F15: =IFERROR(VLOOKUP(E15, Bank!$A$2:$B$421, 2, FALSE), "")
... F420: =IFERROR(VLOOKUP(E420, Bank!$A$2:$B$421, 2, FALSE), "")

Sheet Bank
A1: BankName | B1: Bank Code
A2: 9 payment service Bank | B2: 120001
A3: AB MICROFINANCE BANK | B3: 090270
A4: ABBEY MORTGAGE BANK | B4: 070010
A5: ABOVE ONLY MICROFINANCE BANK | B5: 090260
A6: ABU MICROFINANCE BANK | B6: 090197
A7: ACCESS BANK | B7: 000014
A8: ACCESSMONEY | B8: 100013
A9: ACCION MFB | B9: 090134
A10: ADDOSSER MFBB | B10: 090160
A11: ADEYEMI COLLEGE STAFF MICROFINANCE BANK | B11: 090268
A12: ADVANS LA FAYETTE MFB | B12: 090155
... A421: unilorin Microfinance Bank | B421: 090341
